excel_write/__init__.py
excel_write-1.1.0.dist-info/LICENSE
excel_write-1.1.0.dist-info/METADATA
excel_write-1.1.0.dist-info/WHEEL
excel_write-1.1.0.dist-info/top_level.txt
excel_write-1.1.0.dist-info/RECORD
