Metadata-Version: 2.1
Name: excel-write
Version: 1.1.0
Summary: Optimised way to write in Excel files.
Home-page: https://github.com/themagicalmammal/excel-write
Author: Dipan Nanda
Author-email: d19cyber@gmail.com
License: MIT
Project-URL: Documentation, https://github.com/themagicalmammal/excel-write/blob/main/README.md
Project-URL: Bug tracker, https://github.com/themagicalmammal/excel-write/issues
Keywords: python,excel,pandas,excel-write,write,openpyxl,xlsxwriter
Classifier: Development Status :: 5 - Production/Stable
Classifier: Intended Audience :: Developers
Classifier: License :: OSI Approved :: MIT License
Classifier: Natural Language :: English
Classifier: Programming Language :: Python
Classifier: Programming Language :: Python :: 3
Classifier: Operating System :: Unix
Classifier: Operating System :: MacOS :: MacOS X
Classifier: Operating System :: Microsoft :: Windows
Classifier: Topic :: Utilities
License-File: LICENSE
Requires-Dist: openpyxl (~=3.0.10)
Requires-Dist: pandas (~=1.5.2)
